ipcs/__init__.py
ipcs/__main__.py
ipcs/client.py
ipcs/connection.py
ipcs/errors.py
ipcs/server.py
ipcs/types_.py
ipcs/utils.py
ipcs-0.2.0.dist-info/METADATA
ipcs-0.2.0.dist-info/WHEEL
ipcs-0.2.0.dist-info/entry_points.txt
ipcs-0.2.0.dist-info/licenses/LICENSE
ipcs-0.2.0.dist-info/RECORD
